Workbook

Sheet Assumptions
A1: Holy Sheet! Grazing: Cost Model Assumptions
A2: Blue text on yellow = inputs you can change. Black = formulas. Every other sheet reads from here.
A4: Assumption | B4: Value | C4: Unit | D4: Source / note
A5: Food cost (% of retail price) | B5: 0.35 | C5: % | D5: From your brand playbook financial blueprint (35%).
A6: Labour rate | B6: 35 | C6: $/hr | D6: From your playbook ($35/hr).
A7: Travel & overhead per event | B7: 30 | C7: $ | D7: From your playbook ($30 flat per event). Raise this for venues off the Peninsula.
A8: Kraft paper roll: price | B8: 18.42 | C8: $ | D8: Temu listing, 30 m long heavy brown Kraft roll, AU$18.42 (your screenshot, 20 Sep 2026). Check width and gsm before ordering; playbook recommends 80 gsm or thicker food-grade.
A9: Kraft paper roll: length | B9: 30 | C9: m | D9: Temu listing, 30 m roll.
A10: Kraft paper: cost per metre | B10: =B8/B9 -> 0.614 | C10: $/m | D10: Formula.
A11: Half Sheet: paper length | B11: 1 | C11: m | D11: 60 cm x 100 cm cut, from your menu artwork.
A12: Full Sheet: paper length | B12: 2 | C12: m | D12: 60 cm x 200 cm cut.
A13: Whole Damn Roll: paper length | B13: 5 | C13: m | D13: 60 cm x 400 to 500 cm cut. Using the upper figure.
A14: Half Sheet: labour hours | B14: 2 | C14: hrs | D14: Playbook: 2 hrs.
A15: Full Sheet: labour hours | B15: 3 | C15: hrs | D15: Playbook: 3 hrs.
A16: Whole Damn Roll: labour hours | B16: 5 | C16: hrs | D16: Playbook: 5 hrs.
A17: Disposables per guest (cups, sticks, napkins) | B17: 0.45 | C17: $/guest | D17: Estimate from Temu prices: 60 mini cups $10.97 (18c each), 159 fruit sticks $5.55 (3.5c each), plus napkins. Verify against your actual order.
A18: GST registered? | B18: No | C18: Yes/No | D18: Prices below are treated as GST-free while turnover is under the $75k registration threshold. Confirm with your accountant; once registered, either add 10% to prices or absorb it.

Sheet Startup Shopping List
A1: Startup Shopping List
A2: Temu prices are read from your screenshots (20 Sep 2026) and marked as such. 'Estimate' rows are placeholders for you to replace with real quotes.
A4: Category | B4: Item | C4: Qty | D4: Unit price (AUD) | E4: Line total (AUD) | F4: Source | G4: Notes
A5: Paper | B5: 30 m heavy brown Kraft paper roll | C5: 3 | D5: 18.42 | E5: =C5*D5 -> 55.26 | F5: Temu screenshot | G5: Enough for roughly 30 Half Sheets or 15 Full Sheets per roll. Check width covers 60 cm.
A6: Paper | B6: 9.6 m brown Kraft paper roll (backup / samples) | C6: 1 | D6: 6.8 | E6: =C6*D6 -> 6.8 | F6: Temu screenshot | G6: Handy for sample boxes and test layouts.
A7: Paper | B7: Oilproof food paper, 100 sheets | C7: 2 | D7: 2.52 | E7: =C7*D7 -> 5.04 | F7: Temu screenshot | G7: Barrier layer under oily items (marinated olives, cured meats) so the Kraft stays clean.
A8: Paper | B8: Brown scalloped rosette / doily set, 50 pcs | C8: 1 | D8: 3.6 | E8: =C8*D8 -> 3.6 | F8: Temu screenshot | G8: Styling accents under cheeses.
A9: Serving | B9: 60 pack leak-resistant mini sample cups | C9: 3 | D9: 10.97 | E9: =C9*D9 -> 32.91 | F9: Temu screenshot | G9: Dips, honey, olives. Roughly 3 per 5 guests.
A10: Serving | B10: 159 pcs wooden fruit sticks / picks | C10: 2 | D10: 5.55 | E10: =C10*D10 -> 11.1 | F10: Temu screenshot
A11: Serving | B11: Plastic mini scoops for candy / nuts | C11: 1 | D11: 11.46 | E11: =C11*D11 -> 11.46 | F11: Temu screenshot
A12: Tongs | B12: 6 pc heavy-duty stainless tongs | C12: 2 | D12: 5.4 | E12: =C12*D12 -> 10.8 | F12: Temu screenshot
A13: Tongs | B13: 12 pc mini serving tongs set | C13: 1 | D13: 11.21 | E13: =C13*D13 -> 11.21 | F13: Temu screenshot
A14: Tongs | B14: 5 pc heart-shaped stainless tongs | C14: 2 | D14: 3.38 | E14: =C14*D14 -> 6.76 | F14: Temu screenshot
A15: Tongs | B15: 4 pc salad clips / kitchen tongs | C15: 1 | D15: 4.93 | E15: =C15*D15 -> 4.93 | F15: Temu screenshot
A16: Tongs | B16: 3 pc stainless steel cold food tongs | C16: 1 | D16: 6.47 | E16: =C16*D16 -> 6.47 | F16: Temu screenshot
A17: Tongs | B17: 5 pc gold stainless BBQ / serving tongs | C17: 1 | D17: 11 | E17: =C17*D17 -> 11 | F17: Temu screenshot | G17: Gold finish matches the organic-luxury look.
A18: Tongs | B18: Golden stainless steel mini tongs | C18: 2 | D18: 3.8 | E18: =C18*D18 -> 7.6 | F18: Temu screenshot
A19: Branding | B19: Oversized custom rubber stamp with logo | C19: 1 | D19: 120 | E19: =C19*D19 -> 120 | F19: Estimate: get a quote | G19: Playbook action step 3. Large-format custom stamps run roughly $80 to $180 from Australian stamp makers.
A20: Branding | B20: Food-safe ink pad (brown or charcoal) | C20: 2 | D20: 15 | E20: =C20*D20 -> 30 | F20: Estimate: get a quote | G20: Confirm food-safe rating before stamping near food.
A21: Branding | B21: Domain name (1 year) | C21: 1 | D21: 25 | E21: =C21*D21 -> 25 | F21: Estimate: get a quote | G21: Playbook action step 1. .com.au domains are typically $15 to $35 per year.
A22: Branding | B22: Business cards / thank-you cards (250) | C22: 1 | D22: 60 | E22: =C22*D22 -> 60 | F22: Estimate: get a quote
A23: Compliance | B23: Food safety supervisor certificate | C23: 1 | D23: 150 | E23: =C23*D23 -> 150 | F23: Estimate: get a quote | G23: Required for most Victorian food businesses. Check with Mornington Peninsula Shire for registration under the Food Act.
A24: Compliance | B24: Council food business registration (Class 2 or 3) | C24: 1 | D24: 300 | E24: =C24*D24 -> 300 | F24: Estimate: get a quote | G24: Fee varies by council and class. Confirm with the Shire.
A25: Compliance | B25: Public liability insurance (annual) | C25: 1 | D25: 600 | E25: =C25*D25 -> 600 | F25: Estimate: get a quote | G25: Venues and planners will ask for a certificate of currency.
A26: Kit | B26: Insulated cool bags / eskies | C26: 2 | D26: 45 | E26: =C26*D26 -> 90 | F26: Estimate: get a quote | G26: Cheese and cured meats must travel below 5 degrees C.
A27: Kit | B27: Knives, boards for prep, gloves, cloths | C27: 1 | D27: 120 | E27: =C27*D27 -> 120 | F27: Estimate: get a quote | G27: Prep only; nothing goes on the table but the paper.
A28: Kit | B28: Sample platter boxes for planner outreach (10) | C28: 10 | D28: 4 | E28: =C28*D28 -> 40 | F28: Estimate: get a quote | G28: Playbook pitch email offers a mini sample box to planners.
B29: Total startup spend | E29: =SUM(E5:E28) -> 1719.94
B30: of which Temu consumables and tools | E30: =SUMIFS(E5:E28,F5:F28,"Temu screenshot") -> 184.94
B31: of which estimates still to confirm | E31: =SUMIFS(E5:E28,F5:F28,"Estimate: get a quote") -> 1535

Sheet Package Pricing
A1: Package Pricing & Margin
A2: Retail prices are inputs. Every cost line is a formula driven by the Assumptions sheet.
B4: The Half Sheet | C4: The Full Sheet | D4: The Whole Damn Roll
A5: Guest capacity | B5: 15 | C5: 30 | D5: 60
A6: Retail price (AUD, ex GST) | B6: 550 | C6: 1000 | D6: 1800
A7: Food cost | B7: =B6*Assumptions!$B$5 -> 192.5 | C7: =C6*Assumptions!$B$5 -> 350 | D7: =D6*Assumptions!$B$5 -> 630
A8: Labour hours | B8: =Assumptions!B14 -> 2 | C8: =Assumptions!B15 -> 3 | D8: =Assumptions!B16 -> 5
A9: Labour cost | B9: =B8*Assumptions!$B$6 -> 70 | C9: =C8*Assumptions!$B$6 -> 105 | D9: =D8*Assumptions!$B$6 -> 175
A10: Kraft paper cost | B10: =Assumptions!B11*Assumptions!$B$10 -> 0.614 | C10: =Assumptions!B12*Assumptions!$B$10 -> 1.228 | D10: =Assumptions!B13*Assumptions!$B$10 -> 3.07
A11: Disposables (cups, picks, napkins) | B11: =B5*Assumptions!$B$17 -> 6.75 | C11: =C5*Assumptions!$B$17 -> 13.5 | D11: =D5*Assumptions!$B$17 -> 27
A12: Travel & overhead | B12: =Assumptions!$B$7 -> 30 | C12: =Assumptions!$B$7 -> 30 | D12: =Assumptions!$B$7 -> 30
A13: Total cost | B13: =SUM(B7,B9,B10,B11,B12) -> 299.864 | C13: =SUM(C7,C9,C10,C11,C12) -> 499.728 | D13: =SUM(D7,D9,D10,D11,D12) -> 865.07
A14: Net profit | B14: =B6-B13 -> 250.136 | C14: =C6-C13 -> 500.272 | D14: =D6-D13 -> 934.93
A15: Net profit margin | B15: =IF(B6=0,0,B14/B6) -> 0.45479273 | C15: =IF(C6=0,0,C14/C6) -> 0.500272 | D15: =IF(D6=0,0,D14/D6) -> 0.51940556
A16: Price per guest | B16: =IF(B5=0,0,B6/B5) -> 36.666667 | C16: =IF(C5=0,0,C6/C5) -> 33.333333 | D16: =IF(D5=0,0,D6/D5) -> 30
A17: Profit per labour hour | B17: =IF(B8=0,0,B14/B8) -> 125.068 | C17: =IF(C8=0,0,C14/C8) -> 166.75733 | D17: =IF(D8=0,0,D14/D8) -> 186.986
A19: Playbook comparison (your original blueprint): Half $257.50 / 46.8%, Full $515.00 / 51.5%, Roll $965.00 / 53.6%. This model is slightly lower because it also charges paper and disposables to each event.

Sheet Monthly & Break-even
A1: Monthly Scenario & Startup Break-even
A2: Change the events-per-month inputs to test scenarios. Profit figures flow from Package Pricing.
A4: Package | B4: Events per month | C4: Revenue | D4: Net profit | E4: Labour hours
A5: The Half Sheet | B5: 2 | C5: =B5*'Package Pricing'!B6 -> 1100 | D5: =B5*'Package Pricing'!B14 -> 500.272 | E5: =B5*'Package Pricing'!B8 -> 4
A6: The Full Sheet | B6: 3 | C6: =B6*'Package Pricing'!C6 -> 3000 | D6: =B6*'Package Pricing'!C14 -> 1500.816 | E6: =B6*'Package Pricing'!C8 -> 9
A7: The Whole Damn Roll | B7: 1 | C7: =B7*'Package Pricing'!D6 -> 1800 | D7: =B7*'Package Pricing'!D14 -> 934.93 | E7: =B7*'Package Pricing'!D8 -> 5
A8: Monthly total | B8: =SUM(B5:B7) -> 6 | C8: =SUM(C5:C7) -> 5900 | D8: =SUM(D5:D7) -> 2936.018 | E8: =SUM(E5:E7) -> 18
A10: Total startup spend | B10: ='Startup Shopping List'!E29 -> 1719.94
A11: Months to recover startup spend | B11: =IF(D8<=0,"n/a",B10/D8) -> 0.58580704
A12: Events to recover startup spend (at this mix) | B12: =IF(D8<=0,"n/a",B10/(D8/B8)) -> 3.5148422
A13: Annual net profit at this mix | B13: =D8*12 -> 35232.216
A14: Annual revenue at this mix (GST threshold is $75,000) | B14: =C8*12 -> 70800
A15: Effective hourly earnings (net profit / labour hours) | B15: =IF(E8=0,0,D8/E8) -> 163.11211
A17: Note: the blended event counts above are a starting scenario, not a forecast. Owner labour is costed at the Assumptions labour rate, so 'net profit' is what remains after paying yourself $35/hr.
